{
    "en": {
        "nav": "",
        "foo": "",
        "home": {
            "section0": {},
            "section1": {},
            "section2": {},
            "section3": {}
        },
        "horeca": {
            "section0": {},
            "section1": {},
            "section2": {},
            "section3": {}
        },
        "clothes": {
            "section0": {},
            "section1": {},
            "section2": {},
            "section3": {}
        },
        "decol": {
            "section0": {},
            "section1": {},
            "section2": {},
            "section3": {}
        }
    },
    "ua": {
        "nav": "",
        "foo": "",
        "home": {
            "section0": {},
            "section1": {},
            "section2": {},
            "section3": {}
        },
        "horeca": {
            "section0": {},
            "section1": {},
            "section2": {},
            "section3": {}
        },
        "clothes": {
            "section0": {},
            "section1": {},
            "section2": {},
            "section3": {}
        },
        "decol": {
            "section0": {},
            "section1": {},
            "section2": {},
            "section3": {}
        }
    },
    "fr": {
        "nav": "",
        "foo": "",
        "home": {
            "section0": {},
            "section1": {},
            "section2": {},
            "section3": {}
        },
        "horeca": {
            "section0": {},
            "section1": {},
            "section2": {},
            "section3": {}
        },
        "clothes": {
            "section0": {},
            "section1": {},
            "section2": {},
            "section3": {}
        },
        "decol": {
            "section0": {},
            "section1": {},
            "section2": {},
            "section3": {}
        }
    },
    "de": {
        "nav": "",
        "foo": "",
        "home": {
            "section0": {},
            "section1": {},
            "section2": {},
            "section3": {}
        },
        "horeca": {
            "section0": {},
            "section1": {},
            "section2": {},
            "section3": {}
        },
        "clothes": {
            "section0": {},
            "section1": {},
            "section2": {},
            "section3": {}
        },
        "decol": {
            "section0": {},
            "section1": {},
            "section2": {},
            "section3": {}
        }
    }
}
